SR700_Artisan_Server/.DS_Store
SR700_Artisan_Server/Get_Artisan_Temp.py
SR700_Artisan_Server/Get_Artisan_Temps.py
SR700_Artisan_Server/Get_Artisan_and_Phidget_Temp.py
SR700_Artisan_Server/Get_Roaster_State.py
SR700_Artisan_Server/Roaster_Charge.py
SR700_Artisan_Server/Roaster_Cooling.py
SR700_Artisan_Server/Roaster_Disable_Fan_Manual_Mode.py
SR700_Artisan_Server/Roaster_Disable_Temp_Manual_Mode.py
SR700_Artisan_Server/Roaster_Enable_Fan_Manual_Mode.py
SR700_Artisan_Server/Roaster_Enable_Temp_Manual_Mode.py
SR700_Artisan_Server/Roaster_Preheat.py
SR700_Artisan_Server/Roaster_Set_Fan.py
SR700_Artisan_Server/Roaster_Set_Temp.py
SR700_Artisan_Server/Roaster_Set_Time.py
SR700_Artisan_Server/Roaster_Stop.py
SR700_Artisan_Server/Start_SR700_Artisan_Server.py
SR700_Artisan_Server/__init__.py
SR700_Artisan_Server/alarms/Luca_alarm_150_400_log10_750_sec.alrm
SR700_Artisan_Server/alarms/Luca_profile_based_on_Ryan.alrm
SR700_Artisan_Server/settings/.DS_Store
SR700_Artisan_Server/settings/artisan-settings-no-phidget.aset
SR700_Artisan_Server/settings/artisan-settings.aset
SR700_Artisan_Server-1.6.dist-info/LICENSE
SR700_Artisan_Server-1.6.dist-info/METADATA
SR700_Artisan_Server-1.6.dist-info/WHEEL
SR700_Artisan_Server-1.6.dist-info/entry_points.txt
SR700_Artisan_Server-1.6.dist-info/top_level.txt
SR700_Artisan_Server-1.6.dist-info/RECORD
